BrettonEngNotation/BrettonEngNotation.py
bretton_eng_notation-1.0.1.dist-info/LICENSE
bretton_eng_notation-1.0.1.dist-info/METADATA
bretton_eng_notation-1.0.1.dist-info/WHEEL
bretton_eng_notation-1.0.1.dist-info/top_level.txt
bretton_eng_notation-1.0.1.dist-info/RECORD
