Metadata-Version: 2.2
Name: Bretton_Eng_Notation
Version: 1.0.1
Summary: Converts Numbers Into Engineering Notation
Author-email: Bretton Scarbrough <bretton.scarbrough@gmail.com>
License-File: LICENSE
Requires-Dist: numpy
